celestia_proto/__init__.py
celestia_proto/__init__.pyi
celestia_proto/proofs.proto
celestia_proto/proofs_pb2.py
celestia_proto/proofs_pb2.pyi
celestia_proto/celestia/__init__.py
celestia_proto/celestia/__init__.pyi
celestia_proto/celestia/blob/__init__.py
celestia_proto/celestia/blob/__init__.pyi
celestia_proto/celestia/blob/v1/__init__.py
celestia_proto/celestia/blob/v1/__init__.pyi
celestia_proto/celestia/blob/v1/event.proto
celestia_proto/celestia/blob/v1/event_pb2.py
celestia_proto/celestia/blob/v1/event_pb2.pyi
celestia_proto/celestia/blob/v1/genesis.proto
celestia_proto/celestia/blob/v1/genesis_pb2.py
celestia_proto/celestia/blob/v1/genesis_pb2.pyi
celestia_proto/celestia/blob/v1/params.proto
celestia_proto/celestia/blob/v1/params_pb2.py
celestia_proto/celestia/blob/v1/params_pb2.pyi
celestia_proto/celestia/blob/v1/query.proto
celestia_proto/celestia/blob/v1/query_grpc.py
celestia_proto/celestia/blob/v1/query_pb2.py
celestia_proto/celestia/blob/v1/query_pb2.pyi
celestia_proto/celestia/blob/v1/query_pb2_grpc.py
celestia_proto/celestia/blob/v1/tx.proto
celestia_proto/celestia/blob/v1/tx_pb2.py
celestia_proto/celestia/blob/v1/tx_pb2.pyi
celestia_proto/celestia/core/__init__.py
celestia_proto/celestia/core/__init__.pyi
celestia_proto/celestia/core/v1/__init__.py
celestia_proto/celestia/core/v1/__init__.pyi
celestia_proto/celestia/core/v1/da/__init__.py
celestia_proto/celestia/core/v1/da/__init__.pyi
celestia_proto/celestia/core/v1/da/data_availability_header.proto
celestia_proto/celestia/core/v1/da/data_availability_header_pb2.py
celestia_proto/celestia/core/v1/da/data_availability_header_pb2.pyi
celestia_proto/celestia/core/v1/gas_estimation/__init__.py
celestia_proto/celestia/core/v1/gas_estimation/__init__.pyi
celestia_proto/celestia/core/v1/gas_estimation/gas_estimator.proto
celestia_proto/celestia/core/v1/gas_estimation/gas_estimator_pb2.py
celestia_proto/celestia/core/v1/gas_estimation/gas_estimator_pb2.pyi
celestia_proto/celestia/core/v1/proof/__init__.py
cosmospy_protobuf_celestia-0.6.0.dist-info/METADATA
cosmospy_protobuf_celestia-0.6.0.dist-info/WHEEL
cosmospy_protobuf_celestia-0.6.0.dist-info/RECORD
