Metadata-Version: 2.4
Name: cosmospy_protobuf_celestia
Version: 0.6.0
Summary: This package contains a compiled python version of all celestia protobuf files with their dependencies
Project-URL: Homepage, https://github.com/treenoder/cosmospy-protobuf
Project-URL: Bug Tracker, https://github.com/treenoder/cosmospy-protobuf/issues
Author-email: ctrl-felix <dev@ctrl-felix.de>, treenoder <asymptotelian@gmail.com>
License: BSD 3-Clause License
Keywords: celestia,cosmos,cosmos-protobuf,cosmospy,cosmospy-protobuf,proto,protobuf
Classifier: Operating System :: OS Independent
Classifier: Programming Language :: Python :: 3
Requires-Dist: protobuf<6,>=5
